_getpy.cpython-38-x86_64-linux-gnu.so
getpy/__init__.py
getpy/getpy.py
getpy/getpy_types.py
getpy-0.14.2.dist-info/LICENSE
getpy-0.14.2.dist-info/METADATA
getpy-0.14.2.dist-info/WHEEL
getpy-0.14.2.dist-info/top_level.txt
getpy-0.14.2.dist-info/RECORD
