Metadata-Version: 2.1
Name: getpy
Version: 0.14.2
Summary: A Vectorized Dictionary for Python
Home-page: https://github.com/atom-moyer/getpy
Author: Adam Moyer
Author-email: atom.moyer@gmail.com
License: UNKNOWN
Platform: UNKNOWN
Classifier: Programming Language :: Python :: 3
Classifier: Programming Language :: C++
Classifier: Topic :: Scientific/Engineering
Classifier: Topic :: Software Development
Classifier: License :: OSI Approved :: MIT License
Classifier: Operating System :: Unix
Requires-Dist: numpy
Requires-Dist: pybind11
